calculator_project/__init__.py
calculator_project/calculator.py
irimcalculator-1.0.0.dist-info/LICENSE
irimcalculator-1.0.0.dist-info/METADATA
irimcalculator-1.0.0.dist-info/WHEEL
irimcalculator-1.0.0.dist-info/top_level.txt
irimcalculator-1.0.0.dist-info/RECORD
