Metadata-Version: 2.1
Name: irimcalculator
Version: 1.0.0
Summary: Calculator with bacis operations
Author: Indre Rimkeviciene
Author-email: i.kirsanskaite@gmail.com
License: MIT
Platform: UNKNOWN
License-File: LICENSE
